a_jupyterlite_session/__init__.py
a_jupyterlite_session/_version.py
a_jupyterlite_session-0.2.0.data/data/share/jupyter/labextensions/a-jupyterlite-session/package.json
a_jupyterlite_session-0.2.0.data/data/share/jupyter/labextensions/a-jupyterlite-session/static/262.6f427ce887dd4235c9b1.js
a_jupyterlite_session-0.2.0.data/data/share/jupyter/labextensions/a-jupyterlite-session/static/728.3cd88ca4c82264532afa.js
a_jupyterlite_session-0.2.0.data/data/share/jupyter/labextensions/a-jupyterlite-session/static/961.22e7124f4c9f7bd01868.js
a_jupyterlite_session-0.2.0.data/data/share/jupyter/labextensions/a-jupyterlite-session/static/remoteEntry.e0b28d262622cbca8f2f.js
a_jupyterlite_session-0.2.0.data/data/share/jupyter/labextensions/a-jupyterlite-session/static/style.js
a_jupyterlite_session-0.2.0.data/data/share/jupyter/labextensions/a-jupyterlite-session/static/third-party-licenses.json
a_jupyterlite_session-0.2.0.data/data/share/jupyter/labextensions/a-jupyterlite-session/install.json
a_jupyterlite_session-0.2.0.dist-info/METADATA
a_jupyterlite_session-0.2.0.dist-info/WHEEL
a_jupyterlite_session-0.2.0.dist-info/licenses/LICENSE
a_jupyterlite_session-0.2.0.dist-info/RECORD
